{
    "account-logged-in.svg": [],
    "airplane-mode-symbolic.svg": [],
    "applications-chat-panel.svg": [],
    "applications-email-panel.svg": [],
    "appointment-symbolic.svg": [],
    "microphone-sensitivity-high.svg": [
      "audio-input-microphone-high-panel.svg",
      "audio-input-microphone-high.svg",
      "audio-recorder-on.svg",
      "mic-ready.svg",
      "mic-volume-high.svg",
      "xfce4-mixer-record.svg",
      "audio-input-microphone-none-panel.svg",
      "mic-on.svg"
    ],
    "microphone-sensitivity-low.svg": [
      "audio-input-microphone-low.svg",
      "audio-input-microphone-low-zero-panel.svg",
      "xfce4-mixer-no-record.svg"
    ],
    "microphone-sensitivity-medium.svg": [
      "audio-input-microphone-medium.svg",
      "mic-volume-low.svg",
      "mic-volume-medium.svg"
    ],
    "microphone-sensitivity-muted.svg": [
      "audio-input-microphone-muted.svg",
      "audio-recorder-off.svg",
      "discord-tray-deafened.svg",
      "discord-tray-muted.svg",
      "mic-volume-muted.svg",
      "mic-off.svg"
    ],
    "audio-recorder-paused.svg": [],
    "audio-volume-high-panel.svg": [
      "audio-volume-high.svg",
      "audio-volume-high-symbolic.svg",
      "xfce4-mixer-no-muted.svg",
      "xfce4-mixer-volume-high.svg",
      "xfce4-mixer-volume-very-high.svg",
      "volume-level-high-panel.svg",
      "volume-level-high.svg"
    ],
    "audio-volume-low-panel.svg": [
      "audio-volume-low.svg",
      "audio-volume-low-symbolic.svg",
      "audio-volume-low-zero-panel.svg",
      "xfce4-mixer-volume-low.svg",
      "xfce4-mixer-volume-ultra-low.svg",
      "discord-tray-connected.svg",
      "volume-level-low-panel.svg",
      "volume-level-low.svg"
    ],
    "audio-volume-medium-panel.svg": [
      "audio-volume-medium.svg",
      "audio-volume-medium-symbolic.svg",
      "xfce4-mixer-volume-low-medium.svg",
      "xfce4-mixer-volume-medium.svg",
      "volume-level-medium-panel.svg",
      "volume-level-medium.svg"
    ],
    "audio-volume-muted-blocking-panel.svg": [
      "audio-volume-muted-blocking.svg",
      "audio-volume-muted-panel.svg",
      "audio-volume-muted.svg",
      "audio-volume-muted-blocked-panel.svg",
      "discord-tray-speaking.svg",
      "audio-output-none-panel.svg",
      "audio-output-none.svg",
      "audio-volume-off.svg",
      "volume-level-muted-panel.svg",
      "volume-level-muted.svg",
      "volume-level-none-panel.svg",
      "volume-level-none.svg",
      "xfce4-mixer-muted.svg",
      "xfce4-mixer-volume-muted.svg"
    ],
    "audio-volume-muted-blocking-symbolic.svg": [],
    "audio-volume-muted-symbolic.svg": [],
    "battery-040.svg": [],
    "battery-full-charging.svg": [
      "battery-ac-adapter-symbolic.svg",
      "battery-full-charging-symbolic.svg",
      "gpm-battery-100-charging.svg",
      "gpm-primary-100-charging.svg",
      "gpm-ups-100-charging.svg",
      "xfpm-battery-full-charging.svg",
      "xfpm-primary-100-charging.svg",
      "xfpm-ups-100-charging.svg",
      "battery-100-charging.svg",
      "xfpm-battery-100-charging.svg"
    ],
    "battery-caution-charging.svg": [
      "battery-caution-charging-symbolic.svg",
      "gpm-battery-020-charging.svg",
      "gpm-primary-020-charging.svg",
      "gpm-ups-020-charging.svg",
      "xfce4-battery-caution-charging.svg",
      "xfce4-battery-critical-charging.svg",
      "xfpm-battery-caution-charging.svg",
      "xfpm-battery-critical-charging.svg",
      "xfpm-primary-020-charging.svg",
      "xfpm-ups-020-charging.svg",
      "battery-020-charging.svg",
      "xfpm-battery-020-charging.svg"
    ],
    "battery-caution.svg": [
      "battery-caution-symbolic.svg",
      "gpm-battery-020.svg",
      "gpm-primary-020.svg",
      "gpm-ups-020.svg",
      "xfce4-battery-caution.svg",
      "xfce4-battery-critical.svg",
      "xfpm-battery-caution.svg",
      "xfpm-battery-critical.svg",
      "xfpm-primary-020.svg",
      "xfpm-ups-020.svg",
      "battery-020.svg",
      "xfpm-battery-020.svg"
    ],
    "battery-empty-charging.svg": [
      "battery-empty-charging-symbolic.svg",
      "gpm-battery-000-charging.svg",
      "gpm-primary-000-charging.svg",
      "gpm-ups-000-charging.svg",
      "xfpm-primary-000-charging.svg",
      "xfpm-ups-000-charging.svg",
      "battery-000-charging.svg",
      "xfpm-battery-000-charging.svg"
    ],
    "battery-empty.svg": [
      "battery-empty-symbolic.svg",
      "gpm-battery-000.svg",
      "gpm-primary-000.svg",
      "gpm-ups-000.svg",
      "xfpm-primary-000.svg",
      "xfpm-ups-000.svg",
      "battery-000.svg",
      "gpm-battery-empty.svg",
      "xfpm-battery-000.svg",
      "xfpm-battery-empty.svg"
    ],
    "battery-full.svg": [
      "battery-full-charged.svg",
      "battery-full-symbolic.svg",
      "gpm-battery-100.svg",
      "gpm-primary-100.svg",
      "gpm-ups-100.svg",
      "xfce4-battery-full.svg",
      "xfce4-battery-plugin.svg",
      "xfpm-battery-full.svg",
      "xfpm-primary-100.svg",
      "xfpm-ups-100.svg",
      "battery-full-charged-symbolic.svg",
      "gpm-ac-adapter.svg",
      "gpm-battery-charged.svg",
      "gpm-primary-charged.svg",
      "gpm-ups-charged.svg",
      "xfce4-battery-full-charging.svg",
      "xfpm-primary-charged.svg",
      "xfpm-ups-charged.svg",
      "battery-100.svg",
      "battery_full.svg",
      "xfpm-battery-100.svg",
      "ac-adapter.svg",
      "battery-charged.svg",
      "battery_charged.svg",
      "battery_plugged.svg",
      "xfpm-ac-adapter.svg"
    ],
    "battery-good-charging.svg": [
      "battery-good-charging-symbolic.svg",
      "battery-medium-charging.svg",
      "gpm-battery-060-charging.svg",
      "gpm-battery-080-charging.svg",
      "gpm-primary-060-charging.svg",
      "gpm-primary-080-charging.svg",
      "gpm-ups-060-charging.svg",
      "gpm-ups-080-charging.svg",
      "xfce4-battery-good-charging.svg",
      "xfce4-battery-ok-charging.svg",
      "xfpm-battery-good-charging.svg",
      "xfpm-battery-ok-charging.svg",
      "xfpm-primary-060-charging.svg",
      "xfpm-primary-080-charging.svg",
      "xfpm-ups-060-charging.svg",
      "xfpm-ups-080-charging.svg",
      "battery-060-charging.svg",
      "xfpm-battery-060-charging.svg",
      "battery-080-charging.svg",
      "xfpm-battery-080-charging.svg"
    ],
    "battery-good.svg": [
      "battery-good-symbolic.svg",
      "battery-medium.svg",
      "gpm-battery-060.svg",
      "gpm-battery-080.svg",
      "gpm-primary-060.svg",
      "gpm-primary-080.svg",
      "gpm-ups-060.svg",
      "gpm-ups-080.svg",
      "xfce4-battery-good.svg",
      "xfce4-battery-ok.svg",
      "xfpm-battery-good.svg",
      "xfpm-battery-ok.svg",
      "xfpm-primary-060.svg",
      "xfpm-primary-080.svg",
      "xfpm-ups-060.svg",
      "xfpm-ups-080.svg",
      "battery-060.svg",
      "xfpm-battery-060.svg",
      "battery-080.svg",
      "xfpm-battery-080.svg"
    ],
    "battery-low-charging.svg": [
      "battery-low-charging-symbolic.svg",
      "gpm-battery-040-charging.svg",
      "gpm-primary-040-charging.svg",
      "gpm-ups-040-charging.svg",
      "xfce4-battery-low-charging.svg",
      "xfpm-battery-low-charging.svg",
      "xfpm-primary-040-charging.svg",
      "xfpm-ups-040-charging.svg",
      "battery-040-charging.svg",
      "xfpm-battery-040-charging.svg"
    ],
    "battery-low.svg": [
      "battery-low-symbolic.svg",
      "gpm-battery-040.svg",
      "gpm-primary-040.svg",
      "gpm-ups-040.svg",
      "xfce4-battery-low.svg",
      "xfpm-battery-low.svg",
      "xfpm-primary-040.svg",
      "xfpm-ups-040.svg",
      "xfpm-battery-040.svg"
    ],
    "battery-missing.svg": [
      "battery-missing-symbolic.svg",
      "gpm-battery-missing.svg",
      "gpm-primary-missing.svg",
      "gpm-ups-missing.svg",
      "xfce4-battery-missing.svg",
      "xfpm-primary-missing.svg",
      "xfpm-ups-missing.svg",
      "xfpm-battery-missing.svg"
    ],
    "bluetooth-active.svg": [
      "blueberry-tray-active.svg",
      "blueberry-tray.svg",
      "blueman-active.svg",
      "blueman.svg",
      "blueman-tray-active.svg",
      "blueman-tray.svg",
      "bluetooth-active-symbolic.svg"
    ],
    "bluetooth-disabled.svg": [
      "blueberry-tray-disabled.svg",
      "blueman-disabled.svg",
      "blueman-tray-disabled.svg"
    ],
    "bluetooth-disabled-10-symbolic.svg": [],
    "bluetooth-disabled-20-symbolic.svg": [],
    "bluetooth-disabled-30-symbolic.svg": [],
    "bluetooth-disabled-40-symbolic.svg": [],
    "bluetooth-disabled-50-symbolic.svg": [],
    "bluetooth-disabled-60-symbolic.svg": [],
    "bluetooth-disabled-70-symbolic.svg": [],
    "bluetooth-disabled-80-symbolic.svg": [],
    "bluetooth-disabled-90-symbolic.svg": [],
    "bluetooth-disabled-symbolic.svg": [],
    "bluetooth-paired.svg": [],
    "bluetooth-paired-symbolic.svg": [],
    "caffeine-cup-empty.svg": [],
    "caffeine-cup-full.svg": [],
    "camera-off.svg": [],
    "camera-on.svg": ["camera-ready.svg"],
    "dialog-information-symbolic.svg": [],
    "display-brightness-symbolic.svg": ["notification-display-brightness.svg"],
    "flameshot.svg": ["flameshot-tray.svg", "flameshot-tray.svg"],
    "network-wired-offline.svg": [
      "gnome-netstatus-disconn.svg",
      "knemo-monitor-offline.svg",
      "network-disconnected.svg",
      "network-offline.svg",
      "no-signal.svg",
      "knemo-modem-offline.svg",
      "knemo-network-offline.svg",
      "knemo-wireless-offline.svg"
    ],
    "network-error.svg": [
      "gnome-netstatus-error.svg",
      "knemo-monitor-error.svg",
      "knemo-modem-error.svg",
      "knemo-network-error.svg",
      "knemo-wireless-error.svg"
    ],
    "network-wired.svg": [
      "gnome-netstatus-idle.svg",
      "gnome-netstatus-txrx.svg",
      "knemo-monitor-idle.svg",
      "network-idle.svg",
      "network-transmit-receive.svg",
      "network-wired-symbolic.svg",
      "nm-device-wired.svg",
      "wired.svg",
      "knemo-modem-idle.svg",
      "knemo-monitor-transmit-receive.svg",
      "knemo-network-idle.svg",
      "knemo-wireless-idle.svg",
      "connect_creating.svg",
      "connect_established.svg",
      "nm-device-wired-autoip.svg",
      "knemo-modem-transmit-receive.svg",
      "knemo-network-transmit-receive.svg",
      "knemo-wireless-transmit-receive.svg"
    ],
    "network-receive.svg": [
      "gnome-netstatus-rx.svg",
      "knemo-monitor-receive.svg",
      "knemo-modem-receive.svg",
      "knemo-network-receive.svg",
      "knemo-wireless-receive.svg"
    ],
    "network-transmit.svg": [
      "gnome-netstatus-tx.svg",
      "knemo-monitor-transmit.svg",
      "knemo-modem-transmit.svg",
      "knemo-network-transmit.svg",
      "knemo-wireless-transmit.svg"
    ],
    "gpm-brightness-lcd-disabled.svg": [],
    "gpm-brightness-lcd-invalid.svg": [],
    "gpm-keyboard-000.svg": [],
    "gpm-keyboard-020.svg": [],
    "gpm-keyboard-040.svg": [],
    "gpm-keyboard-060.svg": [],
    "gpm-keyboard-080.svg": [],
    "gpm-keyboard-100.svg": [],
    "network-cellular-secure-signal-excellent.svg": ["gsm-3g-full-secure.svg"],
    "network-cellular-signal-excellent.svg": [
      "gsm-3g-full.svg",
      "nm-wwan-tower.svg",
      "nm-device-wwan.svg"
    ],
    "network-cellular-secure-signal-good.svg": ["gsm-3g-high-secure.svg"],
    "network-cellular-signal-good.svg": ["gsm-3g-high.svg"],
    "network-cellular-secure-signal-low.svg": [
      "gsm-3g-low-secure.svg",
      "network-cellular-secure-signal-weak.svg"
    ],
    "network-cellular-signal-low.svg": [
      "gsm-3g-low.svg",
      "network-cellular-signal-weak.svg"
    ],
    "network-cellular-secure-signal-ok.svg": ["gsm-3g-medium-secure.svg"],
    "network-cellular-signal-ok.svg": ["gsm-3g-medium.svg"],
    "network-cellular-secure-signal-none.svg": ["gsm-3g-none-secure.svg"],
    "network-cellular-signal-none.svg": ["gsm-3g-none.svg"],
    "network-wired-secure.svg": [
      "gtk-dialog-authentication-panel.svg",
      "krb-valid-ticket.svg",
      "network-vpn.svg",
      "network-wired-secure-symbolic.svg",
      "nm-device-wired-secure.svg",
      "nm-device-wired-secureoffline.svg"
    ],
    "indicator-keyboard.svg": ["input-keyboard.svg"],
    "indicator-messages-new.svg": ["xfce-newmail.svg"],
    "indicator-messages-red.svg": [],
    "indicator-messages.svg": ["xfce-nomail.svg"],
    "krb-expiring-ticket.svg": [],
    "krb-no-valid-ticket.svg": [],
    "manjaro.svg": [
      "manjaro-settings-manager-panel.svg",
      "whiskermenu-manjaro.svg",
      "manjaro-settings-manager-panel.svg",
      "whiskermenu-manjaro.svg",
      "manjaro-settings-manager.svg",
      "manjaro-welcome.svg",
      "start-here-manjaro.svg",
      "manjaro-settings-manager.svg",
      "manjaro-welcome.svg",
      "start-here-manjaro.svg"
    ],
    "microphone-sensitivity-muted-10-symbolic.svg": [],
    "microphone-sensitivity-muted-20-symbolic.svg": [],
    "microphone-sensitivity-muted-30-symbolic.svg": [],
    "microphone-sensitivity-muted-40-symbolic.svg": [],
    "microphone-sensitivity-muted-50-symbolic.svg": [],
    "microphone-sensitivity-muted-60-symbolic.svg": [],
    "microphone-sensitivity-muted-70-symbolic.svg": [],
    "microphone-sensitivity-muted-80-symbolic.svg": [],
    "microphone-sensitivity-muted-90-symbolic.svg": [],
    "microphone-sensitivity-muted-symbolic.svg": [],
    "mintupdate-checking.svg": [
      "yum-indicator-updates.svg",
      "yum-indicator-updates.svg"
    ],
    "mintupdate-error.svg": ["yum-indicator-error.svg"],
    "mintupdate-installing.svg": ["yum-indicator-working.svg"],
    "mintupdate-updates-available.svg": [
      "pamac-tray-update.svg",
      "yum-indicator-info.svg",
      "pamac-tray-update.svg"
    ],
    "mintupdate-up-to-date.svg": [
      "pamac-tray-no-update.svg",
      "yum-indicator-no-updates.svg",
      "pamac-tray-no-update.svg",
      "yum-indicator-no-updates.svg"
    ],
    "network-cellular-acquiring.svg": ["network-cellular-signal-acquiring.svg"],
    "network-cellular-acquiring-symbolic.svg": [],
    "network-cellular-connected-symbolic.svg": [],
    "network-cellular-no-route.svg": [],
    "network-cellular-no-route-symbolic.svg": [],
    "network-cellular-offline.svg": [],
    "network-cellular-offline-symbolic.svg": [],
    "network-cellular-signal-excellent-secure-symbolic.svg": [],
    "network-cellular-signal-excellent-symbolic.svg": [],
    "network-cellular-signal-good-secure-symbolic.svg": [],
    "network-cellular-signal-good-symbolic.svg": [],
    "network-cellular-signal-none-secure-symbolic.svg": [],
    "network-cellular-signal-none-symbolic.svg": [],
    "network-cellular-signal-ok-secure-symbolic.svg": [],
    "network-cellular-signal-ok-symbolic.svg": [],
    "network-cellular-signal-weak-secure-symbolic.svg": [],
    "network-cellular-signal-weak-symbolic.svg": [],
    "network-offline-symbolic.svg": [
      "network-wired-disconnected-symbolic.svg",
      "network-wired-offline-symbolic.svg"
    ],
    "network-vpn-acquiring.svg": [],
    "network-vpn-lock-symbolic.svg": [],
    "network-vpn-symbolic.svg": [],
    "network-wired-acquiring.svg": [],
    "network-wired-acquiring-symbolic.svg": [],
    "network-wired-no-route.svg": [],
    "network-wireless-acquiring.svg": [],
    "network-wireless-hotspot.svg": [],
    "network-wireless-no-route.svg": ["network-wireless-no-route-symbolic.svg"],
    "network-wireless-offline.svg": [],
    "nm-signal-100.svg": [
      "network-wireless-connected.svg",
      "network-wireless-signal-excellent.svg",
      "network-wireless-signal-excellent-symbolic.svg",
      "both-high-signal.svg",
      "high-signal.svg",
      "idle-high-signal.svg",
      "receiving-high-signal.svg",
      "transmitting-high-signal.svg",
      "wireless-symbolic.svg",
      "wireless-80-symbolic.svg",
      "network-wireless-100.svg",
      "network-wireless-signal-full-symbolic.svg"
    ],
    "nm-signal-75.svg": [
      "network-wireless-signal-good.svg",
      "network-wireless-signal-good-symbolic.svg",
      "both-good-signal.svg",
      "good-signal.svg",
      "idle-good-signal.svg",
      "receiving-good-signal.svg",
      "network-wireless-.svg",
      "transmitting-good-signal.svg"
    ],
    "nm-signal-50.svg": [
      "network-wireless-signal-ok.svg",
      "both-low-signal.svg",
      "idle-low-signal.svg",
      "low-signal.svg",
      "receiving-low-signal.svg",
      "transmitting-low-signal.svg"
    ],
    "nm-signal-25.svg": [
      "network-wireless-signal-low.svg",
      "network-wireless-signal-ok-symbolic.svg",
      "bad-signal.svg",
      "both-bad-signal.svg",
      "idle-bad-signal.svg",
      "network-wireless-signal-weak.svg",
      "receiving-bad-signal.svg",
      "transmitting-bad-signal.svg"
    ],
    "nm-signal-0.svg": [
      "network-wireless-offline-symbolic.svg",
      "network-wireless-signal-none.svg",
      "network-wireless-signal-none-symbolic.svg",
      "network-wireless-signal-weak-symbolic.svg",
      "nm-no-connection.svg",
      "nm-signal-00.svg",
      "network-wirelss-no-route-symbolic.svg",
      "wireless-disabled-symbolic.svg",
      "wireless-disconnect-symbolic.svg",
      "wireless-0-symbolic.svg",
      "network-wireless-0"
    ],
    "nm-signal-100-secure.svg": [
      "network-wireless-secure-signal-excellent.svg",
      "network-wireless-signal-excellent-secure-symbolic.svg",
      "both-high-signal-lock.svg",
      "high-signal-lock.svg",
      "idle-high-signal-lock.svg",
      "receiving-high-signal-lock.svg",
      "transmitting-high-signal-lock.svg",
      "network-wireless-signal-full-secure-symbolic.svg",
      "network-wireless-100-locked.svg"
    ],
    "nm-signal-75-secure.svg": [
      "network-wireless-secure-signal-good.svg",
      "network-wireless-signal-good-secure-symbolic.svg",
      "both-good-signal-lock.svg",
      "good-signal-lock.svg",
      "idle-good-signal-lock.svg",
      "receiving-good-signal-lock.svg",
      "transmitting-good-signal-lock.svg",
      "network-wireless-signal-high-secure-symbolic.svg"
    ],
    "nm-signal-50-secure.svg": [
      "network-wireless-secure-signal-ok.svg",
      "both-low-signal-lock.svg",
      "idle-low-signal-lock.svg",
      "low-signal-lock.svg",
      "receiving-low-signal-lock.svg",
      "transmitting-low-signal-lock.svg",
      "network-wireless-signal-medium-secure-symbolic.svg"
    ],
    "nm-signal-25-secure.svg": [
      "network-wireless-secure-signal-low.svg",
      "network-wireless-signal-ok-secure-symbolic.svg",
      "bad-signal-lock.svg",
      "both-bad-signal-lock.svg",
      "idle-bad-signal-lock.svg",
      "receiving-bad-signal-lock.svg",
      "transmitting-bad-signal-lock.svg",
      "network-wireless-signal-low-secure-symbolic.svg"
    ],
    "nm-signal-0-secure.svg": [
      "network-wireless-secure-signal-none.svg",
      "network-wireless-signal-weak-secure-symbolic.svg",
      "nm-signal-00-secure.svg",
      "network-wirelss-no-route-secure-symbolic.svg"
    ],
    "night-light-disabled-10-symbolic.svg": [],
    "night-light-disabled-20-symbolic.svg": [],
    "night-light-disabled-30-symbolic.svg": [],
    "night-light-disabled-40-symbolic.svg": [],
    "night-light-disabled-50-symbolic.svg": [],
    "night-light-disabled-60-symbolic.svg": [],
    "night-light-disabled-70-symbolic.svg": [],
    "night-light-disabled-80-symbolic.svg": [],
    "night-light-disabled-90-symbolic.svg": [],
    "night-light-disabled-symbolic.svg": [],
    "night-light-symbolic.svg": [],
    "nm-vpn-lock.svg": ["nm-vpn-active-lock.svg"],
    "notification-disabled-10-symbolic.svg": [],
    "notification-disabled-20-symbolic.svg": [],
    "notification-disabled-30-symbolic.svg": [],
    "notification-disabled-40-symbolic.svg": [],
    "notification-disabled-50-symbolic.svg": [],
    "notification-disabled-60-symbolic.svg": [],
    "notification-disabled-70-symbolic.svg": [],
    "notification-disabled-80-symbolic.svg": [],
    "notification-disabled-90-symbolic.svg": [],
    "notification-disabled-symbolic.svg": [],
    "notification-new-10-symbolic.svg": [],
    "notification-new-20-symbolic.svg": [],
    "notification-new-30-symbolic.svg": [],
    "notification-new-40-symbolic.svg": [],
    "notification-new-50-symbolic.svg": [],
    "notification-new-60-symbolic.svg": [],
    "notification-new-70-symbolic.svg": [],
    "notification-new-80-symbolic.svg": [],
    "notification-new-90-symbolic.svg": [],
    "notification-new-symbolic.svg": [],
    "notification-symbolic.svg": [],
    "onboard-panel.svg": [],
    "optimus-indicator-intel.svg": [],
    "optimus-indicator-nvidia.svg": [],
    "printer-printing-symbolic.svg": [],
    "process-working-symbolic.svg": [],
    "riot-tray.svg": [],
    "slack-indicator-highlight.svg": [],
    "slack-indicator.svg": [],
    "slack-indicator-unread.svg": [],
    "start-here-symbolic.svg": [],
    "state-download.svg": [],
    "state-error.svg": [],
    "state-information.svg": [],
    "state-offline.svg": [],
    "state-ok.svg": [],
    "state-pause.svg": [],
    "state-sync.svg": [],
    "state-warning.svg": [],
    "system-devices-panel.svg": ["system-shutdown-symbolic.svg"],
    "system-search-symbolic.svg": [],
    "telegram-attention-panel.svg": [],
    "telegram-mute-panel.svg": [],
    "telegram-panel.svg": [],
    "uget-tray-default.svg": [],
    "uget-tray-downloading.svg": [],
    "uget-tray-error.svg": [],
    "clipit-trayicon.svg": [],
    "input-touchpad-off.svg": [],
    "input-touchpad-on.svg": [],
    "laptop-connected.svg": [],
    "laptop-disconnected.svg": [],
    "laptop-trusted.svg": [],
    "redshift-status-off.svg": [],
    "redshift-status-on.svg": [],
    "smartphone-connected.svg": [],
    "smartphone-disconnected.svg": [],
    "smartphone-trusted.svg": [],
    "tablet-connected.svg": [],
    "tablet-disconnected.svg": [],
    "tablet-trusted.svg": [],
    "update-high.svg": [],
    "update-low.svg": [],
    "update-medium.svg": [],
    "update-none.svg": []
}
  
